antidxx/__init__.py
antidxx/__main__.py
antidxx/template/message.txt
antidxx/template/sections.txt
antidxx/template/staffs.txt
antidxx-1.0.4.dist-info/METADATA
antidxx-1.0.4.dist-info/WHEEL
antidxx-1.0.4.dist-info/entry_points.txt
antidxx-1.0.4.dist-info/top_level.txt
antidxx-1.0.4.dist-info/RECORD
