Metadata-Version: 2.1
Name: antidxx
Version: 1.0.4
Summary: fast to generate homeworks notices.
Home-page: https://github.com/Mas0nShi/antidaxuexi
Author: Mas0n
Author-email: fishilir@gmail.com
License: UNKNOWN
Keywords: 青春浙江 大学习 daxuexi qczj answers
Platform: UNKNOWN
Classifier: Development Status :: 5 - Production/Stable
Classifier: Operating System :: MacOS :: MacOS X
Classifier: Operating System :: Microsoft :: Windows
Classifier: Operating System :: POSIX :: Linux
Classifier: Programming Language :: Python :: 3.7
Classifier: Programming Language :: Python :: 3.8
Classifier: Programming Language :: Python :: 3.9
Classifier: Programming Language :: Python :: 3.10
Requires-Dist: requests
Requires-Dist: mloguru
Requires-Dist: beautifulsoup4
Requires-Dist: lxml
